svmlite/__init__.py
svmlite/kernels.py
svmlite/metrics.py
svmlite/svm.py
svmlite/utils.py
svmlite-0.1.0.dist-info/licenses/LICENSE
svmlite-0.1.0.dist-info/METADATA
svmlite-0.1.0.dist-info/WHEEL
svmlite-0.1.0.dist-info/top_level.txt
svmlite-0.1.0.dist-info/RECORD
