Metadata-Version: 2.4
Name: svmlite
Version: 0.1.0
Summary: A lightweight SVM implementation from scratch
Author-email: Preet Sojitra <preet.dev373@gmail.com>
License: MIT
Project-URL: Homepage, https://github.com/Preet-Sojitra/SVMLite
Project-URL: Repository, https://github.com/Preet-Sojitra/SVMLite
Requires-Python: >=3.8
License-File: LICENSE
Requires-Dist: numpy>=1.20.0
Provides-Extra: dev
Requires-Dist: pytest>=7.0; extra == "dev"
Requires-Dist: pytest-cov; extra == "dev"
Requires-Dist: black; extra == "dev"
Requires-Dist: flake8; extra == "dev"
Requires-Dist: scikit-learn; extra == "dev"
Dynamic: license-file
